Metadata-Version: 2.1
Name: Lydiabasiccalculator
Version: 0.0.2
Summary: A very basic caluclator
Home-page: 
Author: Lydia Whittaker
Author-email: lydwhitt7@gmail.com
License: MIT
Keywords: calculator
Classifier: Development Status :: 5 - Production/Stable
Classifier: Intended Audience :: Education
Classifier: Operating System :: MacOS
Classifier: License :: OSI Approved :: MIT License
Classifier: Programming Language :: Python :: 3
License-File: LICENSE
License-File: LICENSE.txt
